LICENSE
README.md
setup.cfg
setup.py
a_dcf/__init__.py
a_dcf/a_dcf.py
a_dcf.egg-info/PKG-INFO
a_dcf.egg-info/SOURCES.txt
a_dcf.egg-info/dependency_links.txt
a_dcf.egg-info/top_level.txt