Metadata-Version: 2.1
Name: a-dcf
Version: 0.0.4
Summary: a-dcf preliminary release
Home-page: https://github.com/shimhz/a_dcf
Author: Jee-weon Jung
Author-email: jeeweonj@ieee.org
Keywords: adcf,a-dcf,a_dcf
License-File: LICENSE
